__init__.py
outbox/__init__.py
outbox/handler.py
outbox/protocols.py
outbox/schemas.py
outbox/types.py
outbox/worker.py
outbox_worker-1.0.0.dist-info/METADATA
outbox_worker-1.0.0.dist-info/WHEEL
outbox_worker-1.0.0.dist-info/top_level.txt
outbox_worker-1.0.0.dist-info/RECORD
