Metadata-Version: 2.4
Name: outbox-worker
Version: 1.0.0
Summary: Generic outbox worker for FastStream and custom repositories
Author: k3l3vr444
License: MIT
Requires-Python: >=3.10
Requires-Dist: pydantic>=2.0
Requires-Dist: faststream[rabbit]>=0.5.40
